{
  "when": "2022-02-18T00:26:22.662Z",
  "contracts": {
    "EthereumFarm": [
      {
        "inputs": [
          {
            "internalType": "address",
            "name": "_validator",
            "type": "address"
          }
        ],
        "stateMutability": "nonpayable",
        "type": "constructor"
      },
      {
        "anonymous": false,
        "inputs": [
          {
            "indexed": false,
            "internalType": "uint16",
            "name": "nonce",
            "type": "uint16"
          }
        ],
        "name": "CrossChainPurchase",
        "type": "event"
      },
      {
        "anonymous": false,
        "inputs": [
          {
            "indexed": true,
            "internalType": "address",
            "name": "previousOwner",
            "type": "address"
          },
          {
            "indexed": true,
            "internalType": "address",
            "name": "newOwner",
            "type": "address"
          }
        ],
        "name": "OwnershipTransferred",
        "type": "event"
      },
      {
        "anonymous": false,
        "inputs": [
          {
            "indexed": false,
            "internalType": "address",
            "name": "validator",
            "type": "address"
          }
        ],
        "name": "ValidatorSet",
        "type": "event"
      },
      {
        "inputs": [
          {
            "internalType": "uint8",
            "name": "quantity",
            "type": "uint8"
          },
          {
            "internalType": "uint16",
            "name": "nonce_",
            "type": "uint16"
          },
          {
            "internalType": "uint256",
            "name": "cost",
            "type": "uint256"
          },
          {
            "internalType": "bytes",
            "name": "signature",
            "type": "bytes"
          }
        ],
        "name": "buyTokenCrossChain",
        "outputs": [],
        "stateMutability": "payable",
        "type": "function"
      },
      {
        "inputs": [
          {
            "internalType": "address",
            "name": "to",
            "type": "address"
          },
          {
            "internalType": "uint8",
            "name": "quantity",
            "type": "uint8"
          },
          {
            "internalType": "uint16",
            "name": "nonce_",
            "type": "uint16"
          },
          {
            "internalType": "uint256",
            "name": "cost",
            "type": "uint256"
          }
        ],
        "name": "encodeForSignature",
        "outputs": [
          {
            "internalType": "bytes32",
            "name": "",
            "type": "bytes32"
          }
        ],
        "stateMutability": "pure",
        "type": "function"
      },
      {
        "inputs": [],
        "name": "endSale",
        "outputs": [],
        "stateMutability": "nonpayable",
        "type": "function"
      },
      {
        "inputs": [],
        "name": "owner",
        "outputs": [
          {
            "internalType": "address",
            "name": "",
            "type": "address"
          }
        ],
        "stateMutability": "view",
        "type": "function"
      },
      {
        "inputs": [],
        "name": "proceedsBalance",
        "outputs": [
          {
            "internalType": "uint256",
            "name": "",
            "type": "uint256"
          }
        ],
        "stateMutability": "view",
        "type": "function"
      },
      {
        "inputs": [
          {
            "internalType": "uint16",
            "name": "",
            "type": "uint16"
          }
        ],
        "name": "purchasedTokens",
        "outputs": [
          {
            "internalType": "address",
            "name": "buyer",
            "type": "address"
          },
          {
            "internalType": "uint8",
            "name": "quantity",
            "type": "uint8"
          }
        ],
        "stateMutability": "view",
        "type": "function"
      },
      {
        "inputs": [],
        "name": "renounceOwnership",
        "outputs": [],
        "stateMutability": "nonpayable",
        "type": "function"
      },
      {
        "inputs": [],
        "name": "saleEnded",
        "outputs": [
          {
            "internalType": "bool",
            "name": "",
            "type": "bool"
          }
        ],
        "stateMutability": "view",
        "type": "function"
      },
      {
        "inputs": [
          {
            "internalType": "address",
            "name": "validator_",
            "type": "address"
          }
        ],
        "name": "setValidator",
        "outputs": [],
        "stateMutability": "nonpayable",
        "type": "function"
      },
      {
        "inputs": [
          {
            "internalType": "address",
            "name": "newOwner",
            "type": "address"
          }
        ],
        "name": "transferOwnership",
        "outputs": [],
        "stateMutability": "nonpayable",
        "type": "function"
      },
      {
        "inputs": [],
        "name": "validator",
        "outputs": [
          {
            "internalType": "address",
            "name": "",
            "type": "address"
          }
        ],
        "stateMutability": "view",
        "type": "function"
      },
      {
        "inputs": [
          {
            "internalType": "address",
            "name": "beneficiary",
            "type": "address"
          },
          {
            "internalType": "uint256",
            "name": "amount",
            "type": "uint256"
          }
        ],
        "name": "withdrawProceeds",
        "outputs": [],
        "stateMutability": "nonpayable",
        "type": "function"
      }
    ],
    "Everdragons2Genesis": [
      {
        "inputs": [],
        "stateMutability": "nonpayable",
        "type": "constructor"
      },
      {
        "anonymous": false,
        "inputs": [
          {
            "indexed": false,
            "internalType": "address",
            "name": "previousAdmin",
            "type": "address"
          },
          {
            "indexed": false,
            "internalType": "address",
            "name": "newAdmin",
            "type": "address"
          }
        ],
        "name": "AdminChanged",
        "type": "event"
      },
      {
        "anonymous": false,
        "inputs": [
          {
            "indexed": true,
            "internalType": "address",
            "name": "owner",
            "type": "address"
          },
          {
            "indexed": true,
            "internalType": "address",
            "name": "approved",
            "type": "address"
          },
          {
            "indexed": true,
            "internalType": "uint256",
            "name": "tokenId",
            "type": "uint256"
          }
        ],
        "name": "Approval",
        "type": "event"
      },
      {
        "anonymous": false,
        "inputs": [
          {
            "indexed": true,
            "internalType": "address",
            "name": "owner",
            "type": "address"
          },
          {
            "indexed": true,
            "internalType": "address",
            "name": "operator",
            "type": "address"
          },
          {
            "indexed": false,
            "internalType": "bool",
            "name": "approved",
            "type": "bool"
          }
        ],
        "name": "ApprovalForAll",
        "type": "event"
      },
      {
        "anonymous": false,
        "inputs": [
          {
            "indexed": true,
            "internalType": "uint256",
            "name": "_tokenId",
            "type": "uint256"
          },
          {
            "indexed": true,
            "internalType": "address",
            "name": "_player",
            "type": "address"
          },
          {
            "components": [
              {
                "internalType": "uint8",
                "name": "version",
                "type": "uint8"
              },
              {
                "internalType": "uint8[31]",
                "name": "attributes",
                "type": "uint8[31]"
              }
            ],
            "indexed": false,
            "internalType": "struct IERC721Playable.Attributes",
            "name": "_attributes",
            "type": "tuple"
          }
        ],
        "name": "AttributesSet",
        "type": "event"
      },
      {
        "anonymous": false,
        "inputs": [
          {
            "indexed": true,
            "internalType": "address",
            "name": "beacon",
            "type": "address"
          }
        ],
        "name": "BeaconUpgraded",
        "type": "event"
      },
      {
        "anonymous": false,
        "inputs": [
          {
            "indexed": true,
            "internalType": "address",
            "name": "previousOwner",
            "type": "address"
          },
          {
            "indexed": true,
            "internalType": "address",
            "name": "newOwner",
            "type": "address"
          }
        ],
        "name": "OwnershipTransferred",
        "type": "event"
      },
      {
        "anonymous": false,
        "inputs": [
          {
            "indexed": false,
            "internalType": "address",
            "name": "account",
            "type": "address"
          }
        ],
        "name": "Paused",
        "type": "event"
      },
      {
        "anonymous": false,
        "inputs": [
          {
            "indexed": true,
            "internalType": "address",
            "name": "from",
            "type": "address"
          },
          {
            "indexed": true,
            "internalType": "address",
            "name": "to",
            "type": "address"
          },
          {
            "indexed": true,
            "internalType": "uint256",
            "name": "tokenId",
            "type": "uint256"
          }
        ],
        "name": "Transfer",
        "type": "event"
      },
      {
        "anonymous": false,
        "inputs": [
          {
            "indexed": false,
            "internalType": "address",
            "name": "account",
            "type": "address"
          }
        ],
        "name": "Unpaused",
        "type": "event"
      },
      {
        "anonymous": false,
        "inputs": [
          {
            "indexed": true,
            "internalType": "address",
            "name": "implementation",
            "type": "address"
          }
        ],
        "name": "Upgraded",
        "type": "event"
      },
      {
        "inputs": [
          {
            "internalType": "address",
            "name": "to",
            "type": "address"
          },
          {
            "internalType": "uint256",
            "name": "tokenId",
            "type": "uint256"
          }
        ],
        "name": "approve",
        "outputs": [],
        "stateMutability": "nonpayable",
        "type": "function"
      },
      {
        "inputs": [
          {
            "internalType": "uint256",
            "name": "_tokenId",
            "type": "uint256"
          },
          {
            "internalType": "address",
            "name": "_player",
            "type": "address"
          }
        ],
        "name": "attributesOf",
        "outputs": [
          {
            "components": [
              {
                "internalType": "uint8",
                "name": "version",
                "type": "uint8"
              },
              {
                "internalType": "uint8[31]",
                "name": "attributes",
                "type": "uint8[31]"
              }
            ],
            "internalType": "struct IERC721Playable.Attributes",
            "name": "",
            "type": "tuple"
          }
        ],
        "stateMutability": "view",
        "type": "function"
      },
      {
        "inputs": [
          {
            "internalType": "address",
            "name": "owner",
            "type": "address"
          }
        ],
        "name": "balanceOf",
        "outputs": [
          {
            "internalType": "uint256",
            "name": "",
            "type": "uint256"
          }
        ],
        "stateMutability": "view",
        "type": "function"
      },
      {
        "inputs": [],
        "name": "chainId",
        "outputs": [
          {
            "internalType": "uint16",
            "name": "",
            "type": "uint16"
          }
        ],
        "stateMutability": "view",
        "type": "function"
      },
      {
        "inputs": [],
        "name": "contractURI",
        "outputs": [
          {
            "internalType": "string",
            "name": "",
            "type": "string"
          }
        ],
        "stateMutability": "view",
        "type": "function"
      },
      {
        "inputs": [],
        "name": "endMinting",
        "outputs": [],
        "stateMutability": "nonpayable",
        "type": "function"
      },
      {
        "inputs": [],
        "name": "freezeTokenURI",
        "outputs": [],
        "stateMutability": "nonpayable",
        "type": "function"
      },
      {
        "inputs": [
          {
            "internalType": "uint256",
            "name": "tokenId",
            "type": "uint256"
          }
        ],
        "name": "getApproved",
        "outputs": [
          {
            "internalType": "address",
            "name": "",
            "type": "address"
          }
        ],
        "stateMutability": "view",
        "type": "function"
      },
      {
        "inputs": [
          {
            "internalType": "uint256",
            "name": "_tokenId",
            "type": "uint256"
          },
          {
            "internalType": "address",
            "name": "_player",
            "type": "address"
          }
        ],
        "name": "initAttributes",
        "outputs": [
          {
            "internalType": "bool",
            "name": "",
            "type": "bool"
          }
        ],
        "stateMutability": "nonpayable",
        "type": "function"
      },
      {
        "inputs": [],
        "name": "initialize",
        "outputs": [],
        "stateMutability": "nonpayable",
        "type": "function"
      },
      {
        "inputs": [
          {
            "internalType": "address",
            "name": "owner",
            "type": "address"
          },
          {
            "internalType": "address",
            "name": "operator",
            "type": "address"
          }
        ],
        "name": "isApprovedForAll",
        "outputs": [
          {
            "internalType": "bool",
            "name": "",
            "type": "bool"
          }
        ],
        "stateMutability": "view",
        "type": "function"
      },
      {
        "inputs": [
          {
            "internalType": "bytes32",
            "name": "hash",
            "type": "bytes32"
          }
        ],
        "name": "isTransferCompleted",
        "outputs": [
          {
            "internalType": "bool",
            "name": "",
            "type": "bool"
          }
        ],
        "stateMutability": "view",
        "type": "function"
      },
      {
        "inputs": [],
        "name": "manager",
        "outputs": [
          {
            "internalType": "address",
            "name": "",
            "type": "address"
          }
        ],
        "stateMutability": "view",
        "type": "function"
      },
      {
        "inputs": [
          {
            "internalType": "address",
            "name": "recipient",
            "type": "address"
          },
          {
            "internalType": "uint256",
            "name": "tokenId",
            "type": "uint256"
          }
        ],
        "name": "mint",
        "outputs": [],
        "stateMutability": "nonpayable",
        "type": "function"
      },
      {
        "inputs": [],
        "name": "mintEnded",
        "outputs": [
          {
            "internalType": "bool",
            "name": "",
            "type": "bool"
          }
        ],
        "stateMutability": "view",
        "type": "function"
      },
      {
        "inputs": [],
        "name": "name",
        "outputs": [
          {
            "internalType": "string",
            "name": "",
            "type": "string"
          }
        ],
        "stateMutability": "view",
        "type": "function"
      },
      {
        "inputs": [
          {
            "internalType": "uint16",
            "name": "chainId_",
            "type": "uint16"
          }
        ],
        "name": "nftContract",
        "outputs": [
          {
            "internalType": "bytes32",
            "name": "",
            "type": "bytes32"
          }
        ],
        "stateMutability": "view",
        "type": "function"
      },
      {
        "inputs": [],
        "name": "owner",
        "outputs": [
          {
            "internalType": "address",
            "name": "",
            "type": "address"
          }
        ],
        "stateMutability": "view",
        "type": "function"
      },
      {
        "inputs": [
          {
            "internalType": "uint256",
            "name": "tokenId",
            "type": "uint256"
          }
        ],
        "name": "ownerOf",
        "outputs": [
          {
            "internalType": "address",
            "name": "",
            "type": "address"
          }
        ],
        "stateMutability": "view",
        "type": "function"
      },
      {
        "inputs": [],
        "name": "paused",
        "outputs": [
          {
            "internalType": "bool",
            "name": "",
            "type": "bool"
          }
        ],
        "stateMutability": "view",
        "type": "function"
      },
      {
        "inputs": [],
        "name": "proxiableUUID",
        "outputs": [
          {
            "internalType": "bytes32",
            "name": "",
            "type": "bytes32"
          }
        ],
        "stateMutability": "view",
        "type": "function"
      },
      {
        "inputs": [],
        "name": "renounceOwnership",
        "outputs": [],
        "stateMutability": "nonpayable",
        "type": "function"
      },
      {
        "inputs": [
          {
            "internalType": "address",
            "name": "from",
            "type": "address"
          },
          {
            "internalType": "address",
            "name": "to",
            "type": "address"
          },
          {
            "internalType": "uint256",
            "name": "tokenId",
            "type": "uint256"
          }
        ],
        "name": "safeTransferFrom",
        "outputs": [],
        "stateMutability": "nonpayable",
        "type": "function"
      },
      {
        "inputs": [
          {
            "internalType": "address",
            "name": "from",
            "type": "address"
          },
          {
            "internalType": "address",
            "name": "to",
            "type": "address"
          },
          {
            "internalType": "uint256",
            "name": "tokenId",
            "type": "uint256"
          },
          {
            "internalType": "bytes",
            "name": "_data",
            "type": "bytes"
          }
        ],
        "name": "safeTransferFrom",
        "outputs": [],
        "stateMutability": "nonpayable",
        "type": "function"
      },
      {
        "inputs": [
          {
            "internalType": "address",
            "name": "operator",
            "type": "address"
          },
          {
            "internalType": "bool",
            "name": "approved",
            "type": "bool"
          }
        ],
        "name": "setApprovalForAll",
        "outputs": [],
        "stateMutability": "nonpayable",
        "type": "function"
      },
      {
        "inputs": [
          {
            "internalType": "address",
            "name": "manager_",
            "type": "address"
          }
        ],
        "name": "setManager",
        "outputs": [],
        "stateMutability": "nonpayable",
        "type": "function"
      },
      {
        "inputs": [
          {
            "internalType": "bytes4",
            "name": "interfaceId",
            "type": "bytes4"
          }
        ],
        "name": "supportsInterface",
        "outputs": [
          {
            "internalType": "bool",
            "name": "",
            "type": "bool"
          }
        ],
        "stateMutability": "view",
        "type": "function"
      },
      {
        "inputs": [],
        "name": "symbol",
        "outputs": [
          {
            "internalType": "string",
            "name": "",
            "type": "string"
          }
        ],
        "stateMutability": "view",
        "type": "function"
      },
      {
        "inputs": [
          {
            "internalType": "uint256",
            "name": "index",
            "type": "uint256"
          }
        ],
        "name": "tokenByIndex",
        "outputs": [
          {
            "internalType": "uint256",
            "name": "",
            "type": "uint256"
          }
        ],
        "stateMutability": "view",
        "type": "function"
      },
      {
        "inputs": [
          {
            "internalType": "address",
            "name": "owner",
            "type": "address"
          },
          {
            "internalType": "uint256",
            "name": "index",
            "type": "uint256"
          }
        ],
        "name": "tokenOfOwnerByIndex",
        "outputs": [
          {
            "internalType": "uint256",
            "name": "",
            "type": "uint256"
          }
        ],
        "stateMutability": "view",
        "type": "function"
      },
      {
        "inputs": [
          {
            "internalType": "uint256",
            "name": "tokenId",
            "type": "uint256"
          }
        ],
        "name": "tokenURI",
        "outputs": [
          {
            "internalType": "string",
            "name": "",
            "type": "string"
          }
        ],
        "stateMutability": "view",
        "type": "function"
      },
      {
        "inputs": [],
        "name": "totalSupply",
        "outputs": [
          {
            "internalType": "uint256",
            "name": "",
            "type": "uint256"
          }
        ],
        "stateMutability": "view",
        "type": "function"
      },
      {
        "inputs": [
          {
            "internalType": "address",
            "name": "from",
            "type": "address"
          },
          {
            "internalType": "address",
            "name": "to",
            "type": "address"
          },
          {
            "internalType": "uint256",
            "name": "tokenId",
            "type": "uint256"
          }
        ],
        "name": "transferFrom",
        "outputs": [],
        "stateMutability": "nonpayable",
        "type": "function"
      },
      {
        "inputs": [
          {
            "internalType": "address",
            "name": "newOwner",
            "type": "address"
          }
        ],
        "name": "transferOwnership",
        "outputs": [],
        "stateMutability": "nonpayable",
        "type": "function"
      },
      {
        "inputs": [
          {
            "internalType": "uint256",
            "name": "_tokenId",
            "type": "uint256"
          },
          {
            "internalType": "uint8",
            "name": "_newVersion",
            "type": "uint8"
          },
          {
            "internalType": "uint256[]",
            "name": "_indexes",
            "type": "uint256[]"
          },
          {
            "internalType": "uint8[]",
            "name": "_values",
            "type": "uint8[]"
          }
        ],
        "name": "updateAttributes",
        "outputs": [
          {
            "internalType": "bool",
            "name": "",
            "type": "bool"
          }
        ],
        "stateMutability": "nonpayable",
        "type": "function"
      },
      {
        "inputs": [
          {
            "internalType": "string",
            "name": "uri",
            "type": "string"
          }
        ],
        "name": "updateTokenURI",
        "outputs": [],
        "stateMutability": "nonpayable",
        "type": "function"
      },
      {
        "inputs": [
          {
            "internalType": "address",
            "name": "newImplementation",
            "type": "address"
          }
        ],
        "name": "upgradeTo",
        "outputs": [],
        "stateMutability": "nonpayable",
        "type": "function"
      },
      {
        "inputs": [
          {
            "internalType": "address",
            "name": "newImplementation",
            "type": "address"
          },
          {
            "internalType": "bytes",
            "name": "data",
            "type": "bytes"
          }
        ],
        "name": "upgradeToAndCall",
        "outputs": [],
        "stateMutability": "payable",
        "type": "function"
      },
      {
        "inputs": [],
        "name": "wormhole",
        "outputs": [
          {
            "internalType": "contract IWormhole",
            "name": "",
            "type": "address"
          }
        ],
        "stateMutability": "view",
        "type": "function"
      },
      {
        "inputs": [
          {
            "internalType": "bytes",
            "name": "encodedVm",
            "type": "bytes"
          }
        ],
        "name": "wormholeCompleteTransfer",
        "outputs": [],
        "stateMutability": "nonpayable",
        "type": "function"
      },
      {
        "inputs": [
          {
            "internalType": "uint16",
            "name": "chainId",
            "type": "uint16"
          }
        ],
        "name": "wormholeGetContract",
        "outputs": [
          {
            "internalType": "bytes32",
            "name": "",
            "type": "bytes32"
          }
        ],
        "stateMutability": "view",
        "type": "function"
      },
      {
        "inputs": [
          {
            "internalType": "uint16",
            "name": "chainId",
            "type": "uint16"
          },
          {
            "internalType": "address",
            "name": "wormhole",
            "type": "address"
          }
        ],
        "name": "wormholeInit",
        "outputs": [],
        "stateMutability": "nonpayable",
        "type": "function"
      },
      {
        "inputs": [
          {
            "internalType": "uint16",
            "name": "chainId_",
            "type": "uint16"
          },
          {
            "internalType": "bytes32",
            "name": "nftContract_",
            "type": "bytes32"
          }
        ],
        "name": "wormholeRegisterContract",
        "outputs": [],
        "stateMutability": "nonpayable",
        "type": "function"
      },
      {
        "inputs": [
          {
            "internalType": "uint256",
            "name": "tokenID",
            "type": "uint256"
          },
          {
            "internalType": "uint16",
            "name": "recipientChain",
            "type": "uint16"
          },
          {
            "internalType": "bytes32",
            "name": "recipient",
            "type": "bytes32"
          },
          {
            "internalType": "uint32",
            "name": "nonce",
            "type": "uint32"
          }
        ],
        "name": "wormholeTransfer",
        "outputs": [
          {
            "internalType": "uint64",
            "name": "sequence",
            "type": "uint64"
          }
        ],
        "stateMutability": "payable",
        "type": "function"
      }
    ],
    "Everdragons2GenesisBridged": [
      {
        "inputs": [],
        "stateMutability": "nonpayable",
        "type": "constructor"
      },
      {
        "anonymous": false,
        "inputs": [
          {
            "indexed": false,
            "internalType": "address",
            "name": "previousAdmin",
            "type": "address"
          },
          {
            "indexed": false,
            "internalType": "address",
            "name": "newAdmin",
            "type": "address"
          }
        ],
        "name": "AdminChanged",
        "type": "event"
      },
      {
        "anonymous": false,
        "inputs": [
          {
            "indexed": true,
            "internalType": "address",
            "name": "owner",
            "type": "address"
          },
          {
            "indexed": true,
            "internalType": "address",
            "name": "approved",
            "type": "address"
          },
          {
            "indexed": true,
            "internalType": "uint256",
            "name": "tokenId",
            "type": "uint256"
          }
        ],
        "name": "Approval",
        "type": "event"
      },
      {
        "anonymous": false,
        "inputs": [
          {
            "indexed": true,
            "internalType": "address",
            "name": "owner",
            "type": "address"
          },
          {
            "indexed": true,
            "internalType": "address",
            "name": "operator",
            "type": "address"
          },
          {
            "indexed": false,
            "internalType": "bool",
            "name": "approved",
            "type": "bool"
          }
        ],
        "name": "ApprovalForAll",
        "type": "event"
      },
      {
        "anonymous": false,
        "inputs": [
          {
            "indexed": true,
            "internalType": "uint256",
            "name": "_tokenId",
            "type": "uint256"
          },
          {
            "indexed": true,
            "internalType": "address",
            "name": "_player",
            "type": "address"
          },
          {
            "components": [
              {
                "internalType": "uint8",
                "name": "version",
                "type": "uint8"
              },
              {
                "internalType": "uint8[31]",
                "name": "attributes",
                "type": "uint8[31]"
              }
            ],
            "indexed": false,
            "internalType": "struct IERC721Playable.Attributes",
            "name": "_attributes",
            "type": "tuple"
          }
        ],
        "name": "AttributesSet",
        "type": "event"
      },
      {
        "anonymous": false,
        "inputs": [
          {
            "indexed": true,
            "internalType": "address",
            "name": "beacon",
            "type": "address"
          }
        ],
        "name": "BeaconUpgraded",
        "type": "event"
      },
      {
        "anonymous": false,
        "inputs": [
          {
            "indexed": true,
            "internalType": "address",
            "name": "previousOwner",
            "type": "address"
          },
          {
            "indexed": true,
            "internalType": "address",
            "name": "newOwner",
            "type": "address"
          }
        ],
        "name": "OwnershipTransferred",
        "type": "event"
      },
      {
        "anonymous": false,
        "inputs": [
          {
            "indexed": false,
            "internalType": "address",
            "name": "account",
            "type": "address"
          }
        ],
        "name": "Paused",
        "type": "event"
      },
      {
        "anonymous": false,
        "inputs": [
          {
            "indexed": true,
            "internalType": "address",
            "name": "from",
            "type": "address"
          },
          {
            "indexed": true,
            "internalType": "address",
            "name": "to",
            "type": "address"
          },
          {
            "indexed": true,
            "internalType": "uint256",
            "name": "tokenId",
            "type": "uint256"
          }
        ],
        "name": "Transfer",
        "type": "event"
      },
      {
        "anonymous": false,
        "inputs": [
          {
            "indexed": false,
            "internalType": "address",
            "name": "account",
            "type": "address"
          }
        ],
        "name": "Unpaused",
        "type": "event"
      },
      {
        "anonymous": false,
        "inputs": [
          {
            "indexed": true,
            "internalType": "address",
            "name": "implementation",
            "type": "address"
          }
        ],
        "name": "Upgraded",
        "type": "event"
      },
      {
        "inputs": [
          {
            "internalType": "address",
            "name": "to",
            "type": "address"
          },
          {
            "internalType": "uint256",
            "name": "tokenId",
            "type": "uint256"
          }
        ],
        "name": "approve",
        "outputs": [],
        "stateMutability": "nonpayable",
        "type": "function"
      },
      {
        "inputs": [
          {
            "internalType": "uint256",
            "name": "_tokenId",
            "type": "uint256"
          },
          {
            "internalType": "address",
            "name": "_player",
            "type": "address"
          }
        ],
        "name": "attributesOf",
        "outputs": [
          {
            "components": [
              {
                "internalType": "uint8",
                "name": "version",
                "type": "uint8"
              },
              {
                "internalType": "uint8[31]",
                "name": "attributes",
                "type": "uint8[31]"
              }
            ],
            "internalType": "struct IERC721Playable.Attributes",
            "name": "",
            "type": "tuple"
          }
        ],
        "stateMutability": "view",
        "type": "function"
      },
      {
        "inputs": [
          {
            "internalType": "address",
            "name": "owner",
            "type": "address"
          }
        ],
        "name": "balanceOf",
        "outputs": [
          {
            "internalType": "uint256",
            "name": "",
            "type": "uint256"
          }
        ],
        "stateMutability": "view",
        "type": "function"
      },
      {
        "inputs": [],
        "name": "chainId",
        "outputs": [
          {
            "internalType": "uint16",
            "name": "",
            "type": "uint16"
          }
        ],
        "stateMutability": "view",
        "type": "function"
      },
      {
        "inputs": [],
        "name": "contractURI",
        "outputs": [
          {
            "internalType": "string",
            "name": "",
            "type": "string"
          }
        ],
        "stateMutability": "view",
        "type": "function"
      },
      {
        "inputs": [],
        "name": "freezeTokenURI",
        "outputs": [],
        "stateMutability": "nonpayable",
        "type": "function"
      },
      {
        "inputs": [
          {
            "internalType": "uint256",
            "name": "tokenId",
            "type": "uint256"
          }
        ],
        "name": "getApproved",
        "outputs": [
          {
            "internalType": "address",
            "name": "",
            "type": "address"
          }
        ],
        "stateMutability": "view",
        "type": "function"
      },
      {
        "inputs": [
          {
            "internalType": "uint256",
            "name": "_tokenId",
            "type": "uint256"
          },
          {
            "internalType": "address",
            "name": "_player",
            "type": "address"
          }
        ],
        "name": "initAttributes",
        "outputs": [
          {
            "internalType": "bool",
            "name": "",
            "type": "bool"
          }
        ],
        "stateMutability": "nonpayable",
        "type": "function"
      },
      {
        "inputs": [],
        "name": "initialize",
        "outputs": [],
        "stateMutability": "nonpayable",
        "type": "function"
      },
      {
        "inputs": [
          {
            "internalType": "address",
            "name": "owner",
            "type": "address"
          },
          {
            "internalType": "address",
            "name": "operator",
            "type": "address"
          }
        ],
        "name": "isApprovedForAll",
        "outputs": [
          {
            "internalType": "bool",
            "name": "",
            "type": "bool"
          }
        ],
        "stateMutability": "view",
        "type": "function"
      },
      {
        "inputs": [
          {
            "internalType": "bytes32",
            "name": "hash",
            "type": "bytes32"
          }
        ],
        "name": "isTransferCompleted",
        "outputs": [
          {
            "internalType": "bool",
            "name": "",
            "type": "bool"
          }
        ],
        "stateMutability": "view",
        "type": "function"
      },
      {
        "inputs": [],
        "name": "name",
        "outputs": [
          {
            "internalType": "string",
            "name": "",
            "type": "string"
          }
        ],
        "stateMutability": "view",
        "type": "function"
      },
      {
        "inputs": [
          {
            "internalType": "uint16",
            "name": "chainId_",
            "type": "uint16"
          }
        ],
        "name": "nftContract",
        "outputs": [
          {
            "internalType": "bytes32",
            "name": "",
            "type": "bytes32"
          }
        ],
        "stateMutability": "view",
        "type": "function"
      },
      {
        "inputs": [],
        "name": "owner",
        "outputs": [
          {
            "internalType": "address",
            "name": "",
            "type": "address"
          }
        ],
        "stateMutability": "view",
        "type": "function"
      },
      {
        "inputs": [
          {
            "internalType": "uint256",
            "name": "tokenId",
            "type": "uint256"
          }
        ],
        "name": "ownerOf",
        "outputs": [
          {
            "internalType": "address",
            "name": "",
            "type": "address"
          }
        ],
        "stateMutability": "view",
        "type": "function"
      },
      {
        "inputs": [],
        "name": "paused",
        "outputs": [
          {
            "internalType": "bool",
            "name": "",
            "type": "bool"
          }
        ],
        "stateMutability": "view",
        "type": "function"
      },
      {
        "inputs": [],
        "name": "proxiableUUID",
        "outputs": [
          {
            "internalType": "bytes32",
            "name": "",
            "type": "bytes32"
          }
        ],
        "stateMutability": "view",
        "type": "function"
      },
      {
        "inputs": [],
        "name": "renounceOwnership",
        "outputs": [],
        "stateMutability": "nonpayable",
        "type": "function"
      },
      {
        "inputs": [
          {
            "internalType": "address",
            "name": "from",
            "type": "address"
          },
          {
            "internalType": "address",
            "name": "to",
            "type": "address"
          },
          {
            "internalType": "uint256",
            "name": "tokenId",
            "type": "uint256"
          }
        ],
        "name": "safeTransferFrom",
        "outputs": [],
        "stateMutability": "nonpayable",
        "type": "function"
      },
      {
        "inputs": [
          {
            "internalType": "address",
            "name": "from",
            "type": "address"
          },
          {
            "internalType": "address",
            "name": "to",
            "type": "address"
          },
          {
            "internalType": "uint256",
            "name": "tokenId",
            "type": "uint256"
          },
          {
            "internalType": "bytes",
            "name": "_data",
            "type": "bytes"
          }
        ],
        "name": "safeTransferFrom",
        "outputs": [],
        "stateMutability": "nonpayable",
        "type": "function"
      },
      {
        "inputs": [
          {
            "internalType": "address",
            "name": "operator",
            "type": "address"
          },
          {
            "internalType": "bool",
            "name": "approved",
            "type": "bool"
          }
        ],
        "name": "setApprovalForAll",
        "outputs": [],
        "stateMutability": "nonpayable",
        "type": "function"
      },
      {
        "inputs": [
          {
            "internalType": "bytes4",
            "name": "interfaceId",
            "type": "bytes4"
          }
        ],
        "name": "supportsInterface",
        "outputs": [
          {
            "internalType": "bool",
            "name": "",
            "type": "bool"
          }
        ],
        "stateMutability": "view",
        "type": "function"
      },
      {
        "inputs": [],
        "name": "symbol",
        "outputs": [
          {
            "internalType": "string",
            "name": "",
            "type": "string"
          }
        ],
        "stateMutability": "view",
        "type": "function"
      },
      {
        "inputs": [
          {
            "internalType": "uint256",
            "name": "index",
            "type": "uint256"
          }
        ],
        "name": "tokenByIndex",
        "outputs": [
          {
            "internalType": "uint256",
            "name": "",
            "type": "uint256"
          }
        ],
        "stateMutability": "view",
        "type": "function"
      },
      {
        "inputs": [
          {
            "internalType": "address",
            "name": "owner",
            "type": "address"
          },
          {
            "internalType": "uint256",
            "name": "index",
            "type": "uint256"
          }
        ],
        "name": "tokenOfOwnerByIndex",
        "outputs": [
          {
            "internalType": "uint256",
            "name": "",
            "type": "uint256"
          }
        ],
        "stateMutability": "view",
        "type": "function"
      },
      {
        "inputs": [
          {
            "internalType": "uint256",
            "name": "tokenId",
            "type": "uint256"
          }
        ],
        "name": "tokenURI",
        "outputs": [
          {
            "internalType": "string",
            "name": "",
            "type": "string"
          }
        ],
        "stateMutability": "view",
        "type": "function"
      },
      {
        "inputs": [],
        "name": "totalSupply",
        "outputs": [
          {
            "internalType": "uint256",
            "name": "",
            "type": "uint256"
          }
        ],
        "stateMutability": "view",
        "type": "function"
      },
      {
        "inputs": [
          {
            "internalType": "address",
            "name": "from",
            "type": "address"
          },
          {
            "internalType": "address",
            "name": "to",
            "type": "address"
          },
          {
            "internalType": "uint256",
            "name": "tokenId",
            "type": "uint256"
          }
        ],
        "name": "transferFrom",
        "outputs": [],
        "stateMutability": "nonpayable",
        "type": "function"
      },
      {
        "inputs": [
          {
            "internalType": "address",
            "name": "newOwner",
            "type": "address"
          }
        ],
        "name": "transferOwnership",
        "outputs": [],
        "stateMutability": "nonpayable",
        "type": "function"
      },
      {
        "inputs": [
          {
            "internalType": "uint256",
            "name": "_tokenId",
            "type": "uint256"
          },
          {
            "internalType": "uint8",
            "name": "_newVersion",
            "type": "uint8"
          },
          {
            "internalType": "uint256[]",
            "name": "_indexes",
            "type": "uint256[]"
          },
          {
            "internalType": "uint8[]",
            "name": "_values",
            "type": "uint8[]"
          }
        ],
        "name": "updateAttributes",
        "outputs": [
          {
            "internalType": "bool",
            "name": "",
            "type": "bool"
          }
        ],
        "stateMutability": "nonpayable",
        "type": "function"
      },
      {
        "inputs": [
          {
            "internalType": "string",
            "name": "uri",
            "type": "string"
          }
        ],
        "name": "updateTokenURI",
        "outputs": [],
        "stateMutability": "nonpayable",
        "type": "function"
      },
      {
        "inputs": [
          {
            "internalType": "address",
            "name": "newImplementation",
            "type": "address"
          }
        ],
        "name": "upgradeTo",
        "outputs": [],
        "stateMutability": "nonpayable",
        "type": "function"
      },
      {
        "inputs": [
          {
            "internalType": "address",
            "name": "newImplementation",
            "type": "address"
          },
          {
            "internalType": "bytes",
            "name": "data",
            "type": "bytes"
          }
        ],
        "name": "upgradeToAndCall",
        "outputs": [],
        "stateMutability": "payable",
        "type": "function"
      },
      {
        "inputs": [],
        "name": "wormhole",
        "outputs": [
          {
            "internalType": "contract IWormhole",
            "name": "",
            "type": "address"
          }
        ],
        "stateMutability": "view",
        "type": "function"
      },
      {
        "inputs": [
          {
            "internalType": "bytes",
            "name": "encodedVm",
            "type": "bytes"
          }
        ],
        "name": "wormholeCompleteTransfer",
        "outputs": [],
        "stateMutability": "nonpayable",
        "type": "function"
      },
      {
        "inputs": [
          {
            "internalType": "uint16",
            "name": "chainId",
            "type": "uint16"
          }
        ],
        "name": "wormholeGetContract",
        "outputs": [
          {
            "internalType": "bytes32",
            "name": "",
            "type": "bytes32"
          }
        ],
        "stateMutability": "view",
        "type": "function"
      },
      {
        "inputs": [
          {
            "internalType": "uint16",
            "name": "chainId",
            "type": "uint16"
          },
          {
            "internalType": "address",
            "name": "wormhole",
            "type": "address"
          }
        ],
        "name": "wormholeInit",
        "outputs": [],
        "stateMutability": "nonpayable",
        "type": "function"
      },
      {
        "inputs": [
          {
            "internalType": "uint16",
            "name": "chainId_",
            "type": "uint16"
          },
          {
            "internalType": "bytes32",
            "name": "nftContract_",
            "type": "bytes32"
          }
        ],
        "name": "wormholeRegisterContract",
        "outputs": [],
        "stateMutability": "nonpayable",
        "type": "function"
      },
      {
        "inputs": [
          {
            "internalType": "uint256",
            "name": "tokenID",
            "type": "uint256"
          },
          {
            "internalType": "uint16",
            "name": "recipientChain",
            "type": "uint16"
          },
          {
            "internalType": "bytes32",
            "name": "recipient",
            "type": "bytes32"
          },
          {
            "internalType": "uint32",
            "name": "nonce",
            "type": "uint32"
          }
        ],
        "name": "wormholeTransfer",
        "outputs": [
          {
            "internalType": "uint64",
            "name": "sequence",
            "type": "uint64"
          }
        ],
        "stateMutability": "payable",
        "type": "function"
      }
    ],
    "GenesisFarm": [
      {
        "inputs": [
          {
            "internalType": "contract IEverdragons2Genesis",
            "name": "everdragons2_",
            "type": "address"
          },
          {
            "internalType": "uint256",
            "name": "maxForSale_",
            "type": "uint256"
          },
          {
            "internalType": "uint256",
            "name": "maxClaimable_",
            "type": "uint256"
          },
          {
            "internalType": "uint256",
            "name": "price_",
            "type": "uint256"
          },
          {
            "internalType": "uint256",
            "name": "saleStartAt_",
            "type": "uint256"
          }
        ],
        "stateMutability": "nonpayable",
        "type": "constructor"
      },
      {
        "anonymous": false,
        "inputs": [
          {
            "indexed": true,
            "internalType": "address",
            "name": "previousOwner",
            "type": "address"
          },
          {
            "indexed": true,
            "internalType": "address",
            "name": "newOwner",
            "type": "address"
          }
        ],
        "name": "OwnershipTransferred",
        "type": "event"
      },
      {
        "inputs": [
          {
            "internalType": "uint256",
            "name": "quantity",
            "type": "uint256"
          }
        ],
        "name": "buyTokens",
        "outputs": [],
        "stateMutability": "payable",
        "type": "function"
      },
      {
        "inputs": [
          {
            "internalType": "address",
            "name": "treasury",
            "type": "address"
          },
          {
            "internalType": "uint256",
            "name": "limit",
            "type": "uint256"
          }
        ],
        "name": "claimRemainingTokens",
        "outputs": [],
        "stateMutability": "nonpayable",
        "type": "function"
      },
      {
        "inputs": [
          {
            "internalType": "uint256[]",
            "name": "tokenIds",
            "type": "uint256[]"
          },
          {
            "internalType": "bytes32[]",
            "name": "proof",
            "type": "bytes32[]"
          }
        ],
        "name": "claimWhitelistedTokens",
        "outputs": [],
        "stateMutability": "nonpayable",
        "type": "function"
      },
      {
        "inputs": [],
        "name": "claimingEnded",
        "outputs": [
          {
            "internalType": "bool",
            "name": "",
            "type": "bool"
          }
        ],
        "stateMutability": "view",
        "type": "function"
      },
      {
        "inputs": [
          {
            "internalType": "address",
            "name": "recipient",
            "type": "address"
          },
          {
            "internalType": "uint256[]",
            "name": "tokenIds",
            "type": "uint256[]"
          }
        ],
        "name": "encodeLeaf",
        "outputs": [
          {
            "internalType": "bytes32",
            "name": "",
            "type": "bytes32"
          }
        ],
        "stateMutability": "pure",
        "type": "function"
      },
      {
        "inputs": [],
        "name": "endClaiming",
        "outputs": [],
        "stateMutability": "nonpayable",
        "type": "function"
      },
      {
        "inputs": [],
        "name": "everdragons2Genesis",
        "outputs": [
          {
            "internalType": "contract IEverdragons2Genesis",
            "name": "",
            "type": "address"
          }
        ],
        "stateMutability": "view",
        "type": "function"
      },
      {
        "inputs": [],
        "name": "isManager",
        "outputs": [
          {
            "internalType": "bool",
            "name": "",
            "type": "bool"
          }
        ],
        "stateMutability": "pure",
        "type": "function"
      },
      {
        "inputs": [],
        "name": "maxClaimable",
        "outputs": [
          {
            "internalType": "uint256",
            "name": "",
            "type": "uint256"
          }
        ],
        "stateMutability": "view",
        "type": "function"
      },
      {
        "inputs": [],
        "name": "maxForSale",
        "outputs": [
          {
            "internalType": "uint256",
            "name": "",
            "type": "uint256"
          }
        ],
        "stateMutability": "view",
        "type": "function"
      },
      {
        "inputs": [],
        "name": "nextTokenId",
        "outputs": [
          {
            "internalType": "uint256",
            "name": "",
            "type": "uint256"
          }
        ],
        "stateMutability": "view",
        "type": "function"
      },
      {
        "inputs": [],
        "name": "owner",
        "outputs": [
          {
            "internalType": "address",
            "name": "",
            "type": "address"
          }
        ],
        "stateMutability": "view",
        "type": "function"
      },
      {
        "inputs": [],
        "name": "price",
        "outputs": [
          {
            "internalType": "uint256",
            "name": "",
            "type": "uint256"
          }
        ],
        "stateMutability": "view",
        "type": "function"
      },
      {
        "inputs": [],
        "name": "proceedsBalance",
        "outputs": [
          {
            "internalType": "uint256",
            "name": "",
            "type": "uint256"
          }
        ],
        "stateMutability": "view",
        "type": "function"
      },
      {
        "inputs": [],
        "name": "renounceOwnership",
        "outputs": [],
        "stateMutability": "nonpayable",
        "type": "function"
      },
      {
        "inputs": [],
        "name": "root",
        "outputs": [
          {
            "internalType": "bytes32",
            "name": "",
            "type": "bytes32"
          }
        ],
        "stateMutability": "view",
        "type": "function"
      },
      {
        "inputs": [],
        "name": "saleStartAt",
        "outputs": [
          {
            "internalType": "uint256",
            "name": "",
            "type": "uint256"
          }
        ],
        "stateMutability": "view",
        "type": "function"
      },
      {
        "inputs": [
          {
            "internalType": "bytes32",
            "name": "root_",
            "type": "bytes32"
          }
        ],
        "name": "setRoot",
        "outputs": [],
        "stateMutability": "nonpayable",
        "type": "function"
      },
      {
        "inputs": [
          {
            "internalType": "address",
            "name": "newOwner",
            "type": "address"
          }
        ],
        "name": "transferOwnership",
        "outputs": [],
        "stateMutability": "nonpayable",
        "type": "function"
      },
      {
        "inputs": [
          {
            "internalType": "uint256",
            "name": "maxForSale_",
            "type": "uint256"
          }
        ],
        "name": "updateMaxForSale",
        "outputs": [],
        "stateMutability": "nonpayable",
        "type": "function"
      },
      {
        "inputs": [
          {
            "internalType": "address",
            "name": "beneficiary",
            "type": "address"
          },
          {
            "internalType": "uint256",
            "name": "amount",
            "type": "uint256"
          }
        ],
        "name": "withdrawProceeds",
        "outputs": [],
        "stateMutability": "nonpayable",
        "type": "function"
      }
    ],
    "GenesisFarm2": [
      {
        "inputs": [
          {
            "internalType": "contract IEverdragons2GenesisExtended",
            "name": "everdragons2_",
            "type": "address"
          },
          {
            "internalType": "uint256",
            "name": "maxForSale_",
            "type": "uint256"
          },
          {
            "internalType": "uint256",
            "name": "maxClaimable_",
            "type": "uint256"
          },
          {
            "internalType": "uint256",
            "name": "price_",
            "type": "uint256"
          },
          {
            "internalType": "uint256",
            "name": "extraTokens_",
            "type": "uint256"
          }
        ],
        "stateMutability": "nonpayable",
        "type": "constructor"
      },
      {
        "anonymous": false,
        "inputs": [
          {
            "indexed": true,
            "internalType": "address",
            "name": "previousOwner",
            "type": "address"
          },
          {
            "indexed": true,
            "internalType": "address",
            "name": "newOwner",
            "type": "address"
          }
        ],
        "name": "OwnershipTransferred",
        "type": "event"
      },
      {
        "inputs": [
          {
            "internalType": "uint256",
            "name": "quantity",
            "type": "uint256"
          }
        ],
        "name": "buyTokens",
        "outputs": [],
        "stateMutability": "payable",
        "type": "function"
      },
      {
        "inputs": [
          {
            "internalType": "address",
            "name": "treasury",
            "type": "address"
          },
          {
            "internalType": "uint256",
            "name": "limit",
            "type": "uint256"
          }
        ],
        "name": "claimRemainingTokens",
        "outputs": [],
        "stateMutability": "nonpayable",
        "type": "function"
      },
      {
        "inputs": [
          {
            "internalType": "uint256[]",
            "name": "tokenIds",
            "type": "uint256[]"
          },
          {
            "internalType": "bytes32[]",
            "name": "proof",
            "type": "bytes32[]"
          }
        ],
        "name": "claimWhitelistedTokens",
        "outputs": [],
        "stateMutability": "nonpayable",
        "type": "function"
      },
      {
        "inputs": [],
        "name": "claimingEnded",
        "outputs": [
          {
            "internalType": "bool",
            "name": "",
            "type": "bool"
          }
        ],
        "stateMutability": "view",
        "type": "function"
      },
      {
        "inputs": [
          {
            "internalType": "address",
            "name": "recipient",
            "type": "address"
          },
          {
            "internalType": "uint256[]",
            "name": "tokenIds",
            "type": "uint256[]"
          }
        ],
        "name": "encodeLeaf",
        "outputs": [
          {
            "internalType": "bytes32",
            "name": "",
            "type": "bytes32"
          }
        ],
        "stateMutability": "pure",
        "type": "function"
      },
      {
        "inputs": [],
        "name": "endClaiming",
        "outputs": [],
        "stateMutability": "nonpayable",
        "type": "function"
      },
      {
        "inputs": [],
        "name": "everdragons2Genesis",
        "outputs": [
          {
            "internalType": "contract IEverdragons2GenesisExtended",
            "name": "",
            "type": "address"
          }
        ],
        "stateMutability": "view",
        "type": "function"
      },
      {
        "inputs": [],
        "name": "extraTokens",
        "outputs": [
          {
            "internalType": "uint256",
            "name": "",
            "type": "uint256"
          }
        ],
        "stateMutability": "view",
        "type": "function"
      },
      {
        "inputs": [
          {
            "internalType": "uint256",
            "name": "",
            "type": "uint256"
          }
        ],
        "name": "firstBuyers",
        "outputs": [
          {
            "internalType": "address",
            "name": "",
            "type": "address"
          }
        ],
        "stateMutability": "view",
        "type": "function"
      },
      {
        "inputs": [
          {
            "internalType": "address",
            "name": "",
            "type": "address"
          }
        ],
        "name": "firstBuyersBalance",
        "outputs": [
          {
            "internalType": "uint256",
            "name": "",
            "type": "uint256"
          }
        ],
        "stateMutability": "view",
        "type": "function"
      },
      {
        "inputs": [
          {
            "internalType": "uint256",
            "name": "index",
            "type": "uint256"
          },
          {
            "internalType": "uint256",
            "name": "max",
            "type": "uint256"
          }
        ],
        "name": "giveExtraTokens",
        "outputs": [],
        "stateMutability": "nonpayable",
        "type": "function"
      },
      {
        "inputs": [],
        "name": "isManager",
        "outputs": [
          {
            "internalType": "bool",
            "name": "",
            "type": "bool"
          }
        ],
        "stateMutability": "pure",
        "type": "function"
      },
      {
        "inputs": [],
        "name": "maxClaimable",
        "outputs": [
          {
            "internalType": "uint256",
            "name": "",
            "type": "uint256"
          }
        ],
        "stateMutability": "view",
        "type": "function"
      },
      {
        "inputs": [],
        "name": "maxForSale",
        "outputs": [
          {
            "internalType": "uint256",
            "name": "",
            "type": "uint256"
          }
        ],
        "stateMutability": "view",
        "type": "function"
      },
      {
        "inputs": [],
        "name": "nextTokenId",
        "outputs": [
          {
            "internalType": "uint256",
            "name": "",
            "type": "uint256"
          }
        ],
        "stateMutability": "view",
        "type": "function"
      },
      {
        "inputs": [],
        "name": "owner",
        "outputs": [
          {
            "internalType": "address",
            "name": "",
            "type": "address"
          }
        ],
        "stateMutability": "view",
        "type": "function"
      },
      {
        "inputs": [],
        "name": "price",
        "outputs": [
          {
            "internalType": "uint256",
            "name": "",
            "type": "uint256"
          }
        ],
        "stateMutability": "view",
        "type": "function"
      },
      {
        "inputs": [],
        "name": "proceedsBalance",
        "outputs": [
          {
            "internalType": "uint256",
            "name": "",
            "type": "uint256"
          }
        ],
        "stateMutability": "view",
        "type": "function"
      },
      {
        "inputs": [],
        "name": "renounceOwnership",
        "outputs": [],
        "stateMutability": "nonpayable",
        "type": "function"
      },
      {
        "inputs": [],
        "name": "root",
        "outputs": [
          {
            "internalType": "bytes32",
            "name": "",
            "type": "bytes32"
          }
        ],
        "stateMutability": "view",
        "type": "function"
      },
      {
        "inputs": [
          {
            "internalType": "bytes32",
            "name": "root_",
            "type": "bytes32"
          }
        ],
        "name": "setRoot",
        "outputs": [],
        "stateMutability": "nonpayable",
        "type": "function"
      },
      {
        "inputs": [],
        "name": "totalFirstBuyers",
        "outputs": [
          {
            "internalType": "uint256",
            "name": "",
            "type": "uint256"
          }
        ],
        "stateMutability": "view",
        "type": "function"
      },
      {
        "inputs": [
          {
            "internalType": "address",
            "name": "newOwner",
            "type": "address"
          }
        ],
        "name": "transferOwnership",
        "outputs": [],
        "stateMutability": "nonpayable",
        "type": "function"
      },
      {
        "inputs": [
          {
            "internalType": "uint256",
            "name": "maxForSale_",
            "type": "uint256"
          }
        ],
        "name": "updateMaxForSale",
        "outputs": [],
        "stateMutability": "nonpayable",
        "type": "function"
      },
      {
        "inputs": [
          {
            "internalType": "uint256",
            "name": "price_",
            "type": "uint256"
          }
        ],
        "name": "updatePrice",
        "outputs": [],
        "stateMutability": "nonpayable",
        "type": "function"
      },
      {
        "inputs": [
          {
            "internalType": "address",
            "name": "beneficiary",
            "type": "address"
          },
          {
            "internalType": "uint256",
            "name": "amount",
            "type": "uint256"
          }
        ],
        "name": "withdrawProceeds",
        "outputs": [],
        "stateMutability": "nonpayable",
        "type": "function"
      }
    ],
    "GenesisFarm3": [
      {
        "inputs": [
          {
            "internalType": "contract IEverdragons2GenesisExtended",
            "name": "everdragons2_",
            "type": "address"
          },
          {
            "internalType": "uint256",
            "name": "maxForSale_",
            "type": "uint256"
          },
          {
            "internalType": "uint256",
            "name": "maxClaimable_",
            "type": "uint256"
          },
          {
            "internalType": "address",
            "name": "operator_",
            "type": "address"
          }
        ],
        "stateMutability": "nonpayable",
        "type": "constructor"
      },
      {
        "anonymous": false,
        "inputs": [
          {
            "indexed": false,
            "internalType": "address",
            "name": "operator",
            "type": "address"
          }
        ],
        "name": "OperatorSet",
        "type": "event"
      },
      {
        "anonymous": false,
        "inputs": [
          {
            "indexed": true,
            "internalType": "address",
            "name": "previousOwner",
            "type": "address"
          },
          {
            "indexed": true,
            "internalType": "address",
            "name": "newOwner",
            "type": "address"
          }
        ],
        "name": "OwnershipTransferred",
        "type": "event"
      },
      {
        "inputs": [
          {
            "internalType": "address[]",
            "name": "recipients",
            "type": "address[]"
          },
          {
            "internalType": "uint256[][]",
            "name": "tokenIds",
            "type": "uint256[][]"
          },
          {
            "internalType": "bytes32[][]",
            "name": "proof",
            "type": "bytes32[][]"
          }
        ],
        "name": "batchDelegatedClaimWhitelistedTokens",
        "outputs": [],
        "stateMutability": "nonpayable",
        "type": "function"
      },
      {
        "inputs": [
          {
            "internalType": "uint256",
            "name": "quantity",
            "type": "uint256"
          }
        ],
        "name": "buyTokens",
        "outputs": [],
        "stateMutability": "payable",
        "type": "function"
      },
      {
        "inputs": [
          {
            "internalType": "address",
            "name": "treasury",
            "type": "address"
          },
          {
            "internalType": "uint256",
            "name": "limit",
            "type": "uint256"
          }
        ],
        "name": "claimRemainingTokens",
        "outputs": [],
        "stateMutability": "nonpayable",
        "type": "function"
      },
      {
        "inputs": [
          {
            "internalType": "uint256[]",
            "name": "tokenIds",
            "type": "uint256[]"
          },
          {
            "internalType": "bytes32[]",
            "name": "proof",
            "type": "bytes32[]"
          }
        ],
        "name": "claimWhitelistedTokens",
        "outputs": [],
        "stateMutability": "nonpayable",
        "type": "function"
      },
      {
        "inputs": [],
        "name": "claimingEnded",
        "outputs": [
          {
            "internalType": "bool",
            "name": "",
            "type": "bool"
          }
        ],
        "stateMutability": "view",
        "type": "function"
      },
      {
        "inputs": [
          {
            "internalType": "address",
            "name": "recipient",
            "type": "address"
          },
          {
            "internalType": "uint256[]",
            "name": "tokenIds",
            "type": "uint256[]"
          },
          {
            "internalType": "bytes32[]",
            "name": "proof",
            "type": "bytes32[]"
          }
        ],
        "name": "delegatedClaimWhitelistedTokens",
        "outputs": [],
        "stateMutability": "nonpayable",
        "type": "function"
      },
      {
        "inputs": [
          {
            "internalType": "address",
            "name": "buyer",
            "type": "address"
          },
          {
            "internalType": "uint256",
            "name": "quantity",
            "type": "uint256"
          }
        ],
        "name": "deliverCrossChainPurchase",
        "outputs": [],
        "stateMutability": "nonpayable",
        "type": "function"
      },
      {
        "inputs": [
          {
            "internalType": "address",
            "name": "recipient",
            "type": "address"
          },
          {
            "internalType": "uint256[]",
            "name": "tokenIds",
            "type": "uint256[]"
          }
        ],
        "name": "encodeLeaf",
        "outputs": [
          {
            "internalType": "bytes32",
            "name": "",
            "type": "bytes32"
          }
        ],
        "stateMutability": "pure",
        "type": "function"
      },
      {
        "inputs": [],
        "name": "endClaiming",
        "outputs": [],
        "stateMutability": "nonpayable",
        "type": "function"
      },
      {
        "inputs": [],
        "name": "everdragons2Genesis",
        "outputs": [
          {
            "internalType": "contract IEverdragons2GenesisExtended",
            "name": "",
            "type": "address"
          }
        ],
        "stateMutability": "view",
        "type": "function"
      },
      {
        "inputs": [],
        "name": "getChainId",
        "outputs": [
          {
            "internalType": "uint256",
            "name": "",
            "type": "uint256"
          }
        ],
        "stateMutability": "view",
        "type": "function"
      },
      {
        "inputs": [],
        "name": "isManager",
        "outputs": [
          {
            "internalType": "bool",
            "name": "",
            "type": "bool"
          }
        ],
        "stateMutability": "pure",
        "type": "function"
      },
      {
        "inputs": [],
        "name": "maxClaimable",
        "outputs": [
          {
            "internalType": "uint256",
            "name": "",
            "type": "uint256"
          }
        ],
        "stateMutability": "view",
        "type": "function"
      },
      {
        "inputs": [],
        "name": "maxForSale",
        "outputs": [
          {
            "internalType": "uint256",
            "name": "",
            "type": "uint256"
          }
        ],
        "stateMutability": "view",
        "type": "function"
      },
      {
        "inputs": [],
        "name": "nextTokenId",
        "outputs": [
          {
            "internalType": "uint256",
            "name": "",
            "type": "uint256"
          }
        ],
        "stateMutability": "view",
        "type": "function"
      },
      {
        "inputs": [],
        "name": "operator",
        "outputs": [
          {
            "internalType": "address",
            "name": "",
            "type": "address"
          }
        ],
        "stateMutability": "view",
        "type": "function"
      },
      {
        "inputs": [],
        "name": "owner",
        "outputs": [
          {
            "internalType": "address",
            "name": "",
            "type": "address"
          }
        ],
        "stateMutability": "view",
        "type": "function"
      },
      {
        "inputs": [
          {
            "internalType": "uint256",
            "name": "lastId",
            "type": "uint256"
          }
        ],
        "name": "price",
        "outputs": [
          {
            "internalType": "uint256",
            "name": "",
            "type": "uint256"
          }
        ],
        "stateMutability": "view",
        "type": "function"
      },
      {
        "inputs": [],
        "name": "proceedsBalance",
        "outputs": [
          {
            "internalType": "uint256",
            "name": "",
            "type": "uint256"
          }
        ],
        "stateMutability": "view",
        "type": "function"
      },
      {
        "inputs": [],
        "name": "renounceOwnership",
        "outputs": [],
        "stateMutability": "nonpayable",
        "type": "function"
      },
      {
        "inputs": [],
        "name": "root",
        "outputs": [
          {
            "internalType": "bytes32",
            "name": "",
            "type": "bytes32"
          }
        ],
        "stateMutability": "view",
        "type": "function"
      },
      {
        "inputs": [
          {
            "internalType": "address",
            "name": "operator_",
            "type": "address"
          }
        ],
        "name": "setOperator",
        "outputs": [],
        "stateMutability": "nonpayable",
        "type": "function"
      },
      {
        "inputs": [
          {
            "internalType": "bytes32",
            "name": "root_",
            "type": "bytes32"
          }
        ],
        "name": "setRoot",
        "outputs": [],
        "stateMutability": "nonpayable",
        "type": "function"
      },
      {
        "inputs": [
          {
            "internalType": "address",
            "name": "newOwner",
            "type": "address"
          }
        ],
        "name": "transferOwnership",
        "outputs": [],
        "stateMutability": "nonpayable",
        "type": "function"
      },
      {
        "inputs": [
          {
            "internalType": "uint256",
            "name": "maxForSale_",
            "type": "uint256"
          }
        ],
        "name": "updateMaxForSale",
        "outputs": [],
        "stateMutability": "nonpayable",
        "type": "function"
      },
      {
        "inputs": [
          {
            "internalType": "address",
            "name": "beneficiary",
            "type": "address"
          },
          {
            "internalType": "uint256",
            "name": "amount",
            "type": "uint256"
          }
        ],
        "name": "withdrawProceeds",
        "outputs": [],
        "stateMutability": "nonpayable",
        "type": "function"
      }
    ]
  }
}